{
  "QueueUrl": "https://sqs.eu-west-1.amazonaws.com/211125758836/notification-fanout",
  "Attributes": {
    "QueueArn": "arn:aws:sqs:eu-west-1:211125758836:notification-fanout",
    "VisibilityTimeout": "180",
    "MessageRetentionPeriod": "345600",
    "MaximumMessageSize": "262144",
    "DelaySeconds": "0",
    "ReceiveMessageWaitTimeSeconds": "20",
    "SqsManagedSseEnabled": "true",
    "Policy": "{\"Version\":\"2012-10-17\",\"Id\":\"notification-fanout-policy\",\"Statement\":[{\"Sid\":\"AllowSnsTopic\",\"Effect\":\"Allow\",\"Principal\":\"*\",\"Action\":\"sqs:SendMessage\",\"Resource\":\"arn:aws:sqs:eu-west-1:211125758836:notification-fanout\",\"Condition\":{\"ArnEquals\":{\"aws:SourceArn\":\"arn:aws:sns:eu-west-1:211125758836:account-events\"}}}]}",
    "RedrivePolicy": "{\"deadLetterTargetArn\":\"arn:aws:sqs:eu-west-1:211125758836:notification-fanout-dlq\",\"maxReceiveCount\":5}",
    "ApproximateNumberOfMessages": "14",
    "CreatedTimestamp": "1737974400",
    "LastModifiedTimestamp": "1748000000"
  }
}
